{"name":"satococoa","tagline":"Satoshi Ebisawa","body":"### Satoshi Ebisawa\r\nWeb, iOS エンジニアです。\r\n\r\n- Blog(Japanese): http://satococoa.hatenablog.com\r\n- Facebook: https://www.facebook.com/satoshi.ebisawa\r\n- Twitter: https://twitter.com/satococoa\r\n- GitHub: satococoa\r\n- Presentations: https://speakerdeck.com/satococoa\r\n\r\n### 運営コミュニティ等\r\n\r\n- [P4D (デザイナー向けプログラム部)](http://prog4designer.github.io)\r\n- [ゆるふわ Development Club](http://yurufuwa.club)","google":"UA-32351198-1","note":"Don't delete this file! It's used internally to help with page regeneration."}